LICENSE
LICENSE.txt
README.md
setup.cfg
setup.py
medium_scrapper/__init__.py
medium_scrapper/scrapper.py
medium_scrapper/utils.py
medium_scrapper.egg-info/PKG-INFO
medium_scrapper.egg-info/SOURCES.txt
medium_scrapper.egg-info/dependency_links.txt
medium_scrapper.egg-info/requires.txt
medium_scrapper.egg-info/top_level.txt