Metadata-Version: 2.1
Name: medium-scrapper
Version: 0.1
Summary: Scrapping tools to get information about medium articles
Home-page: https://github.com/addicted-by/medium_scrapper
Download-URL: https://github.com/addicted-by/medium_scrapper/archive/refs/tags/v0.1.tar.gz
Author: Aleksey Ryabykin
Author-email: ras.unlucky@yandex.ru
License: MIT
Keywords: scrapping,medium articles,selenium
Classifier: Development Status :: 3 - Alpha
Classifier: Intended Audience :: Developers
Classifier: Topic :: Software Development :: Build Tools
Classifier: License :: OSI Approved :: MIT License
Classifier: Programming Language :: Python :: 3
Classifier: Programming Language :: Python :: 3.4
Classifier: Programming Language :: Python :: 3.5
Classifier: Programming Language :: Python :: 3.6
Classifier: Programming Language :: Python :: 3.7
Classifier: Programming Language :: Python :: 3.8
Classifier: Programming Language :: Python :: 3.9
Classifier: Programming Language :: Python :: 3.10
License-File: LICENSE
License-File: LICENSE.txt
